Metadata-Version: 2.1
Name: patosyadir
Version: 0.0.1
Summary: patosya package
Home-page: UNKNOWN
Author: Skidanov EA
Author-email: your@domain.com
License: UNKNOWN
Platform: UNKNOWN
